KFSmath/KFSmath.py
kfsmath-1.0.2.dist-info/METADATA
kfsmath-1.0.2.dist-info/WHEEL
kfsmath-1.0.2.dist-info/RECORD
