Metadata-Version: 2.1
Name: KFSmath
Version: 1.0.2
Summary: 
Home-page: https://github.com/9-FS/2023-09-20-KFSmath
License: MIT
Author: 9FS
Author-email: pray4spam@googlemail.com
Requires-Python: >=3.12.0,<4.0.0
Classifier: License :: OSI Approved :: MIT License
Classifier: Programming Language :: Python :: 3
Classifier: Programming Language :: Python :: 3.12
Project-URL: Repository, https://github.com/9-FS/2023-09-20-KFSmath
